legibilidad
