Metadata-Version: 1.0
Name: legibilidad
Version: 0.21
Summary: Spanish text readability calculation
Home-page: https://gitlab.com/__alexander__/legibilidad
Author: Alexander Ayasca
Author-email: alexander.ayasca.esquives@gmail.com
License: MIT
Platform: UNKNOWN
